{
  "game_id": "0022401158",
  "teams": [
    "TOR",
    "CHA"
  ],
  "outliers": [
    {
      "positive": [
        {
          "type": "player",
          "name": "A.J. Lawson",
          "stat": "A.J. Lawson - AST",
          "score": 7.225,
          "actual": 7,
          "avg": 1.19,
          "player_id": 1630639
        },
        {
          "type": "player",
          "name": "Jonathan Mogbo",
          "stat": "Jonathan Mogbo - AST",
          "score": 6.817,
          "actual": 11,
          "avg": 2.32,
          "player_id": 1642367
        },
        {
          "type": "player",
          "name": "Nick Smith Jr.",
          "stat": "Nick Smith Jr. - AST",
          "score": 5.793,
          "actual": 10,
          "avg": 2.42,
          "player_id": 1641733
        },
        {
          "type": "player",
          "name": "Nick Smith Jr.",
          "stat": "Nick Smith Jr. - PTS",
          "score": 4.856,
          "actual": 28,
          "avg": 9.85,
          "player_id": 1641733
        },
        {
          "type": "player",
          "name": "Jusuf Nurki\u0107",
          "stat": "Jusuf Nurki\u0107 - PTS",
          "score": 4.848,
          "actual": 26,
          "avg": 8.88,
          "player_id": 203994
        }
      ],
      "negative": [
        {
          "type": "team",
          "name": "Charlotte Hornets",
          "stat": "Charlotte Hornets - OREB",
          "score": -2.15,
          "actual": 5,
          "avg": 12.23,
          "team_abbr": "CHA"
        },
        {
          "type": "player",
          "name": "RJ Barrett",
          "stat": "RJ Barrett - PTS",
          "score": -1.799,
          "actual": 11,
          "avg": 21.09,
          "player_id": 1629628
        },
        {
          "type": "player",
          "name": "Jaylen Sims",
          "stat": "Jaylen Sims - FG3_PCT",
          "score": -1.183,
          "actual": 0.0,
          "avg": 0.4,
          "player_id": 1631301
        },
        {
          "type": "player",
          "name": "Jusuf Nurki\u0107",
          "stat": "Jusuf Nurki\u0107 - FG3_PCT",
          "score": -1.118,
          "actual": 0.0,
          "avg": 0.25,
          "player_id": 203994
        },
        {
          "type": "player",
          "name": "Orlando Robinson",
          "stat": "Orlando Robinson - FG3_PCT",
          "score": -1.1,
          "actual": 0.0,
          "avg": 0.21,
          "player_id": 1631115
        }
      ]
    }
  ],
  "final_score": {
    "TOR": 126,
    "CHA": 96
  },
  "winner": "TOR"
}