{
  "game_id": "22401186",
  "teams": [
    "ATL",
    "ORL"
  ],
  "outliers": [
    {
      "positive": [
        {
          "type": "player",
          "name": "Jacob Toppin",
          "stat": "Jacob Toppin - PTS",
          "score": 15.0,
          "actual": 17,
          "avg": 1.35
        },
        {
          "type": "player",
          "name": "Keaton Wallace",
          "stat": "Keaton Wallace - AST",
          "score": 11.868,
          "actual": 15,
          "avg": 2.61
        },
        {
          "type": "player",
          "name": "Keaton Wallace",
          "stat": "Keaton Wallace - REB",
          "score": 10.0,
          "actual": 11,
          "avg": 1.61
        },
        {
          "type": "player",
          "name": "Gary Harris",
          "stat": "Gary Harris - PTS",
          "score": 8.921,
          "actual": 12,
          "avg": 3.02
        },
        {
          "type": "player",
          "name": "Jett Howard",
          "stat": "Jett Howard - PTS",
          "score": 7.787,
          "actual": 16,
          "avg": 4.45
        }
      ],
      "negative": [
        {
          "type": "player",
          "name": "Keaton Wallace",
          "stat": "Keaton Wallace - TOV",
          "score": -3.66,
          "actual": 3,
          "avg": 1.06
        },
        {
          "type": "player",
          "name": "Dominick Barlow",
          "stat": "Dominick Barlow - PF",
          "score": -2.978,
          "actual": 4,
          "avg": 1.34
        },
        {
          "type": "player",
          "name": "Jett Howard",
          "stat": "Jett Howard - PF",
          "score": -2.482,
          "actual": 3,
          "avg": 1.13
        },
        {
          "type": "player",
          "name": "Daeqwon Plowden",
          "stat": "Daeqwon Plowden - PF",
          "score": -2.093,
          "actual": 4,
          "avg": 1.67
        },
        {
          "type": "player",
          "name": "Keaton Wallace",
          "stat": "Keaton Wallace - PF",
          "score": -2.071,
          "actual": 3,
          "avg": 1.26
        }
      ]
    }
  ]
}